vibromaf/__init__.py
vibromaf/metrics/__init__.py
vibromaf/metrics/snr.py
vibromaf/metrics/spqi.py
vibromaf/metrics/stsim.py
vibromaf/metrics/vibromaf.py
vibromaf/signal/__init__.py
vibromaf/signal/perception.py
vibromaf/signal/spectrum.py
vibromaf/signal/transform.py
vibromaf/util/__init__.py
vibromaf/util/common.py
vibromaf/util/matlab.py
vibromaf/util/model.py
vibromaf-0.0.8.dist-info/LICENSE.md
vibromaf-0.0.8.dist-info/METADATA
vibromaf-0.0.8.dist-info/WHEEL
vibromaf-0.0.8.dist-info/top_level.txt
vibromaf-0.0.8.dist-info/RECORD
