Metadata-Version: 2.1
Name: vibromaf
Version: 0.0.8
Summary: Vibrotactile quality metrics and metric fusion
Home-page: https://github.com/hofbi/vibromaf
Author: Markus Hofbauer, Andreas Noll
Author-email: name.surname@tum.de
License: MIT
Project-URL: Bug Tracker, https://github.com/hofbi/vibromaf/issues
Project-URL: Discussions, https://github.com/hofbi/vibromaf/discussions
Project-URL: Documentation, https://hofbi.github.io/vibromaf
Keywords: haptics,vibrotactile quality assessment,signal processing
Classifier: License :: OSI Approved :: MIT License
Classifier: Operating System :: OS Independent
Classifier: Intended Audience :: Developers
Classifier: License :: OSI Approved :: MIT License
Classifier: Natural Language :: English
Classifier: Programming Language :: Python :: 3
Classifier: Programming Language :: Python :: 3.9
Classifier: Programming Language :: Python :: 3.10
Classifier: Programming Language :: Python :: 3.11
Classifier: Programming Language :: Python :: 3.12
Classifier: Programming Language :: Python :: 3.13
Requires-Python: >=3.9
License-File: LICENSE.md
Requires-Dist: numpy
Requires-Dist: scikit-learn
Requires-Dist: scipy
